[ {
  "number" : 1,
  "text" : "O Senhor é o meu pastor; nada me falta."
}, {
  "number" : 2,
  "text" : "Em verdes prados me faz descansar, e para águas tranquilas me guia em paz."
}, {
  "number" : 3,
  "text" : "Restaura-me o vigor e conduz-me nos caminhos da justiça por amor do seu Nome."
}, {
  "number" : 4,
  "text" : "Ainda que eu ande pelo vale da sombra da morte, não temerei mal algum, pois tu estás comigo; a tua vara e o teu cajado me protegem."
}, {
  "number" : 5,
  "text" : "Tu prepararás um banquete para mim na presença dos meus inimigos; me honrarás,"
}, {
  "number" : 6,
  "text" : "A felicidade e a misericórdia certamente me acompanharão todos os dias da minha vida; e habitarei na Casa do Senhor por dias sem fim."
} ]