[ {
  "number" : 1,
  "text" : "Quando Jeová reconduziu os cativos de Sião, éramos como aqueles que estão sonhando."
}, {
  "number" : 2,
  "text" : "Então, a nossa boca se encheu de riso, e a nossa língua, de júbilo. Dizia-se, então, entre as nações: Grandes coisas tem feito Jeová por eles."
}, {
  "number" : 3,
  "text" : "Grandes coisas tem feito Jeová por nós; somos cheios de júbilo."
}, {
  "number" : 4,
  "text" : "Faze, Jeová, voltar os nossos cativos como as torrentes no Neguebe."
}, {
  "number" : 5,
  "text" : "Aqueles que semeiam em lágrimas com júbilo ceifarão."
}, {
  "number" : 6,
  "text" : "Embora alguém saia chorando, levando a semente para semear, tornará a vir com júbilo, trazendo os seus feixes."
} ]