[ {
  "number" : 1,
  "text" : "O SENHOR Deus é Rei. Alegre-se a terra! Fiquem contentes, ilhas dos mares!"
}, {
  "number" : 2,
  "text" : "Em volta dele há nuvens e escuridão; as bases do seu reinado são a honestidade e a justiça."
}, {
  "number" : 3,
  "text" : "Na sua frente, vai um fogo que queima os inimigos ao seu redor."
}, {
  "number" : 4,
  "text" : "Os seus relâmpagos iluminam o mundo; a terra vê e treme."
}, {
  "number" : 5,
  "text" : "Os montes se derretem como cera diante do SENHOR, diante do Senhor de toda a terra."
}, {
  "number" : 6,
  "text" : "Os céus anunciam a sua justiça, e todos os povos veem a sua glória."
}, {
  "number" : 7,
  "text" : "Os que adoram imagens ficam envergonhados; passam vergonha os que se gabam dos seus ídolos. Diante de Deus, o SENHOR, todos os deuses se curvam."
}, {
  "number" : 8,
  "text" : "Por causa dos teus julgamentos, ó SENHOR, o povo de Jerusalém está contente, e as cidades de Judá se alegram."
}, {
  "number" : 9,
  "text" : "Ó SENHOR, Deus Altíssimo, tu governas o mundo inteiro, tu estás acima de todos os deuses."
}, {
  "number" : 10,
  "text" : "Vocês, que amam a Deus, o SENHOR, odeiem o mal; ele protege a vida dos que lhe são fiéis e os livra do poder dos maus."
}, {
  "number" : 11,
  "text" : "A luz ilumina a vida dos honestos, e a alegria ilumina o caminho dos que obedecem a Deus."
}, {
  "number" : 12,
  "text" : "Que o SENHOR seja a alegria de vocês que são obedientes a ele! Que o Santo Deus seja louvado!"
} ]