[ {
  "number" : 1,
  "text" : "Aleluia! Louvai, servos do SENHOR, louvai o nome do SENHOR!"
}, {
  "number" : 2,
  "text" : "Bendito seja o nome do SENHOR, desde agora e para sempre!"
}, {
  "number" : 3,
  "text" : "Do nascer ao pôr do sol, louvado seja o nome do SENHOR!"
}, {
  "number" : 4,
  "text" : "O SENHOR é exaltado acima de todas as nações, e sua glória está acima dos céus."
}, {
  "number" : 5,
  "text" : "Quem é semelhante ao SENHOR, nosso Deus, que se assenta nas alturas,"
}, {
  "number" : 6,
  "text" : "que se inclina para ver o que está no céu e na terra?"
}, {
  "number" : 7,
  "text" : "Do pó levanta o pobre, e da miséria ergue o necessitado,"
}, {
  "number" : 8,
  "text" : "para fazê-lo sentar-se com os príncipes, sim, com os príncipes do seu povo."
}, {
  "number" : 9,
  "text" : "Ele faz com que a mulher estéril viva em família e, alegre, seja mãe de filhos. Aleluia!"
} ]