[ {
  "number" : 1,
  "text" : "Desde a mocidade tenho sofrido horríveis perseguições; que o povo de Israel responda:"
}, {
  "number" : 2,
  "text" : "Desde a mocidade tenho sofrido horríveis perseguições, mas ninguém foi capaz de me destruir!"
}, {
  "number" : 3,
  "text" : "As minhas costas têm marcas profundas, como os sulcos feitos pelo arado."
}, {
  "number" : 4,
  "text" : "O SENHOR é justo e me livrou das cordas dos maus."
}, {
  "number" : 5,
  "text" : "Deus há de envergonhar e derrotar todos os povos que odeiam Sião."
}, {
  "number" : 6,
  "text" : "Eles serão como o capim que cresce no terraço, que seca e murcha antes de ser arrancada,"
}, {
  "number" : 7,
  "text" : "capim que ninguém colhe, nem o prende em feixes."
}, {
  "number" : 8,
  "text" : "Quem passar diante dessas pessoas não diga: “A bênção do SENHOR esteja sobre vocês! Nós os abençoamos em nome do SENHOR!”"
} ]